{
	"info": {
		"_postman_id": "3a74c02a-06ac-4cd3-9774-0959833e2eb5",
		"name": "TestHackathonJobServices",
		"schema": "https://schema.getpostman.com/json/collection/v2.1.0/collection.json"
	},
	"item": [
		{
			"name": "GetAllJobs",
			"request": {
				"method": "GET",
				"header": [],
				"url": {
					"raw": "http://localhost:8080/api/jobs",
					"protocol": "http",
					"host": [
						"localhost"
					],
					"port": "8080",
					"path": [
						"api",
						"jobs"
					]
				}
			},
			"response": []
		},
		{
			"name": "TriggerJob",
			"request": {
				"method": "POST",
				"header": [
					{
						"key": "Content-Type",
						"name": "Content-Type",
						"value": "application/json",
						"type": "text"
					}
				],
				"body": {
					"mode": "raw",
					"raw": ""
				},
				"url": {
					"raw": "http://localhost:8080/api/job/1",
					"protocol": "http",
					"host": [
						"localhost"
					],
					"port": "8080",
					"path": [
						"api",
						"job",
						"1"
					]
				}
			},
			"response": []
		}
	]
}